zarvan/__init__.py
zarvan/config.py
zarvan/model.py
zarvan-0.2.2.dist-info/licenses/LICENSE
zarvan-0.2.2.dist-info/METADATA
zarvan-0.2.2.dist-info/WHEEL
zarvan-0.2.2.dist-info/top_level.txt
zarvan-0.2.2.dist-info/RECORD
