Metadata-Version: 2.4
Name: zarvan
Version: 0.2.2
Summary: Zarvan: A Hybrid MoE Architecture for Advanced Sequence Modeling.
Author-email: Yasser Sajjadi <yassersajjadi@gmail.com>
License:                                  Apache License
Project-URL: Homepage, https://github.com/systbs/zarvan-torch
Project-URL: Issues, https://github.com/systbs/zarvan-torch/issues
Classifier: Programming Language :: Python :: 3
Classifier: License :: OSI Approved :: Apache Software License
Classifier: Operating System :: OS Independent
Classifier: Intended Audience :: Science/Research
Classifier: Topic :: Scientific/Engineering :: Artificial Intelligence
Requires-Python: >=3.8
License-File: LICENSE
Requires-Dist: torch>=2.0.0
Requires-Dist: torchaudio>=2.0.0
Dynamic: license-file
